maestro2charmmgui/__init__.py
maestro2charmmgui/name_maps.py
maestro2charmmgui/rename.py
maestro2charmmgui-0.1.6.dist-info/METADATA
maestro2charmmgui-0.1.6.dist-info/WHEEL
maestro2charmmgui-0.1.6.dist-info/RECORD
