Metadata-Version: 2.1
Name: maestro2charmmgui
Version: 0.1.6
Summary: PDB Format transformation from Maestro to CHARMM-GUI. This can make the CHARMM-GUI recognise the original orientation of the hydrogen atoms generated by Maestro.
Author: Yu-Yuan (Stuart) Yang, AFLab
Author-email: yu-yuan.yang@qmul.ac.uk
Requires-Python: >=3.8,<4.0
Classifier: Programming Language :: Python :: 3
Classifier: Programming Language :: Python :: 3.8
Classifier: Programming Language :: Python :: 3.9
Classifier: Programming Language :: Python :: 3.10
Classifier: Programming Language :: Python :: 3.11
Classifier: Programming Language :: Python :: 3.12
Requires-Dist: mdanalysis (>=2.4,<3.0)
Requires-Dist: pytest (>=7.4.4,<8.0.0)
Requires-Dist: pytest-cov (>=4.1.0,<5.0.0)
